cfgdict/__init__.py
cfgdict/api.py
cfgdict/exception.py
cfgdict/field.py
cfgdict/logger.py
cfgdict/schema.py
cfgdict/utils.py
cfgdict/v1.py
cfgdict/v2.py
cfgdict/version.py
cfgdict-1.1.3.dist-info/LICENSE
cfgdict-1.1.3.dist-info/METADATA
cfgdict-1.1.3.dist-info/WHEEL
cfgdict-1.1.3.dist-info/top_level.txt
cfgdict-1.1.3.dist-info/RECORD
