Metadata-Version: 2.1
Name: cfgdict
Version: 1.1.3
Summary: A lightweight dict-like config library with validation support
Home-page: http://github.com/gseismic/cfgdict
Author: Liu Shengli
Author-email: liushengli203@163.com
Project-URL: Source, https://github.com/gseismic/cfgdict
Classifier: Environment :: Web Environment
Classifier: Intended Audience :: Developers
Classifier: License :: OSI Approved :: MIT License
Classifier: Natural Language :: English
Classifier: Operating System :: OS Independent
Classifier: Programming Language :: Python :: 3
Classifier: Programming Language :: Python :: 3.8
Classifier: Programming Language :: Python :: 3.9
Classifier: Programming Language :: Python :: 3.10
Classifier: Programming Language :: Python :: 3.11
Classifier: Programming Language :: Python :: 3.12
Classifier: Programming Language :: Python :: 3.13
Classifier: Programming Language :: Python :: Implementation :: PyPy
Classifier: Topic :: Software Development :: Libraries
Classifier: Topic :: Utilities
Requires-Python: >=3
License-File: LICENSE
Requires-Dist: loguru
Requires-Dist: pyyaml
Requires-Dist: arrow
